bispy/__init__.py
bispy/filters.py
bispy/qfft.py
bispy/signals.py
bispy/spectral.py
bispy/timefrequency.py
bispy/utils.py
bispy_polar-0.9.4.dev0.dist-info/LICENCE
bispy_polar-0.9.4.dev0.dist-info/METADATA
bispy_polar-0.9.4.dev0.dist-info/WHEEL
bispy_polar-0.9.4.dev0.dist-info/top_level.txt
bispy_polar-0.9.4.dev0.dist-info/RECORD
