Metadata-Version: 2.1
Name: bispy-polar
Version: 0.9.4.dev0
Summary: An open-source python framework for processing     bivariate signals.
Home-page: https://github.com/jflamant/bispy
Author: Julien Flamant
Author-email: julien.flamant@cnrs.fr
License: CeCIll
Keywords: signal processing
Classifier: Development Status :: 3 - Alpha
Classifier: Intended Audience :: Science/Research
Classifier: License :: OSI Approved :: MIT License
Classifier: Programming Language :: Python :: 3.5
License-File: LICENCE
Requires-Dist: numpy
Requires-Dist: scipy
Requires-Dist: matplotlib
Requires-Dist: numpy-quaternion
Provides-Extra: dev
Requires-Dist: check-manifest ; extra == 'dev'
Provides-Extra: test
Requires-Dist: coverage ; extra == 'test'
